{
    "last_updated": "2026-07-09T00:02:47.444577+00:00",
    "metro": {
        "aqi": 126,
        "lst": 25.7,
        "air_temp": 25.2,
        "rain_mm": 0.0
    },
    "districts": {
        "Ba Dinh": {
            "aqi": 141,
            "lst": 30.2,
            "flood_points": 9
        },
        "Hoan Kiem": {
            "aqi": 144,
            "lst": 30.6,
            "flood_points": 9
        },
        "Tay Ho": {
            "aqi": 119,
            "lst": 25.4,
            "flood_points": 3
        },
        "Long Bien": {
            "aqi": 128,
            "lst": 25.2,
            "flood_points": 2
        },
        "Cau Giay": {
            "aqi": 151,
            "lst": 30.0,
            "flood_points": 9
        },
        "Dong Da": {
            "aqi": 148,
            "lst": 31.7,
            "flood_points": 13
        },
        "Hai Ba Trung": {
            "aqi": 143,
            "lst": 31.6,
            "flood_points": 11
        },
        "Hoang Mai": {
            "aqi": 142,
            "lst": 26.7,
            "flood_points": 4
        },
        "Thanh Xuan": {
            "aqi": 146,
            "lst": 31.7,
            "flood_points": 11
        },
        "Soc Son": {
            "aqi": 90,
            "lst": 24.0,
            "flood_points": 1
        },
        "Dong Anh": {
            "aqi": 123,
            "lst": 24.3,
            "flood_points": 1
        },
        "Gia Lam": {
            "aqi": 119,
            "lst": 24.4,
            "flood_points": 1
        },
        "Thanh Tri": {
            "aqi": 131,
            "lst": 24.9,
            "flood_points": 2
        },
        "Bac Tu Liem": {
            "aqi": 131,
            "lst": 25.8,
            "flood_points": 3
        },
        "Nam Tu Liem": {
            "aqi": 136,
            "lst": 25.9,
            "flood_points": 3
        },
        "Me Linh": {
            "aqi": 110,
            "lst": 24.2,
            "flood_points": 1
        },
        "Ha Dong": {
            "aqi": 136,
            "lst": 25.9,
            "flood_points": 3
        },
        "Son Tay": {
            "aqi": 100,
            "lst": 24.1,
            "flood_points": 1
        },
        "Ba Vi": {
            "aqi": 75,
            "lst": 23.9,
            "flood_points": 1
        },
        "Phuc Tho": {
            "aqi": 93,
            "lst": 24.1,
            "flood_points": 1
        },
        "Dan Phuong": {
            "aqi": 98,
            "lst": 24.3,
            "flood_points": 1
        },
        "Hoai Duc": {
            "aqi": 120,
            "lst": 24.6,
            "flood_points": 2
        },
        "Quoc Oai": {
            "aqi": 95,
            "lst": 24.1,
            "flood_points": 1
        },
        "Thach That": {
            "aqi": 103,
            "lst": 24.2,
            "flood_points": 1
        },
        "Chuong My": {
            "aqi": 98,
            "lst": 24.1,
            "flood_points": 1
        },
        "Thanh Oai": {
            "aqi": 105,
            "lst": 24.1,
            "flood_points": 1
        },
        "Thuong Tin": {
            "aqi": 110,
            "lst": 24.2,
            "flood_points": 1
        },
        "Phu Xuyen": {
            "aqi": 103,
            "lst": 24.0,
            "flood_points": 1
        },
        "Ung Hoa": {
            "aqi": 93,
            "lst": 24.0,
            "flood_points": 1
        },
        "My Duc": {
            "aqi": 83,
            "lst": 24.0,
            "flood_points": 1
        }
    },
    "debug_logs": [
        "Station Hanoi US Embassy, Vietnam (Đại sứ quán Mỹ, Hà Nội) returned non-numeric AQI: -",
        "Endpoint https://api.waqi.info/feed/vietnam/hanoi/french-embassy/ returned status: error",
        "Endpoint https://api.waqi.info/feed/vietnam/hanoi/chi-cuc-bvmt-hanoi/ returned status: error",
        "Station Hanoi, Vietnam (Hà Nội) returned non-numeric AQI: -",
        "Fetched AQI from United Nations International School of Hanoi, Vietnam (Trường Quốc tế Liên Hợp Quốc Hà Nội): 126",
        "Selected realistic AQI 126 from United Nations International School of Hanoi, Vietnam (Trường Quốc tế Liên Hợp Quốc Hà Nội)",
        "Successfully fetched weather: Temp=25.2°C, SoilTemp=25.7°C, Rain=0.0mm"
    ]
}